excelgdb/__init__.py
excelgdb/model/__init__.py
excelgdb/model/mainClass.py
excelgdb/mutils/__init__.py
excelgdb/mutils/line_lyr.py
excelgdb/mutils/point_lyr.py
excelgdb/mutils/polygon_lyr.py
excelgdb/test/test.py
excelgdb/test/Data/hospital.xlsx
excelgdb/test/Data/railway.xlsx
excelgdb/test/Data/shahrestan.xlsx
excelgdb-0.4.dist-info/METADATA
excelgdb-0.4.dist-info/WHEEL
excelgdb-0.4.dist-info/top_level.txt
excelgdb-0.4.dist-info/RECORD
