Metadata-Version: 2.1
Name: excelgdb
Version: 0.4
Summary: A toolkit for converting Excel coordinates to ArcGIS GDB
Home-page: https://github.com/ali-hasanvand/excelgdb.git
Author: Hasanvand
Author-email: ali.mohamad.hassanvand@gmail.com
Classifier: Programming Language :: Python :: 3
Classifier: License :: OSI Approved :: MIT License
Classifier: Operating System :: OS Independent
